{
  "updated": [
    {
      "id": "602cb333-b862-4635-af8c-2856a10d2784",
      "name": "SUPERCUTS",
      "category_key": "health-wellness",
      "url": "https://seeklogo.com/vector-logo/264518/supercuts"
    },
    {
      "id": "47425c19-dbab-47b2-8940-51d6a5dd553c",
      "name": "Mathnasium",
      "category_key": "home-services",
      "url": "https://mathnasiumfranchise.com/resources/assets/images/franchise/logo.png"
    },
    {
      "id": "84e3afd8-a3a3-45ee-be8d-0b99c6778b1e",
      "name": "Alex Monsalve Law Firm",
      "category_key": "professional-services",
      "url": "https://www.alexmonsalvelawfirm.com/assets/logo.png"
    },
    {
      "id": "f56ac5dd-52ff-4445-81a5-52c6d61dbb7d",
      "name": "Archer & Associates",
      "category_key": "professional-services",
      "url": "https://archer-associates.com/about/associates/image.jpg"
    },
    {
      "id": "33523e9d-9c4b-4963-a269-500376e57543",
      "name": "Armas Business Consultants",
      "category_key": "professional-services",
      "url": "https://www.armabusinessconsulting.com/assets/images/logo.png"
    },
    {
      "id": "47d11314-f5bd-4d59-8d8c-3bb0f687df43",
      "name": "Arroyo Law Center",
      "category_key": "professional-services",
      "url": "https://scontent.xx.fbcdn.net/v/t1.6435-9/1557687888871694.jpg?_nc_cat=111&ccb=1-5&_nc_sid=9267fe&_nc_ohc=Z0231SGeLNoAX_ESFJy&_nc_ht=scontent.xx&oh=00_AfCEXBZa3n_UYk-DgTuXM98n00QNhdCMCMmUJfu_Mzg4Cw&oe=60C75283"
    },
    {
      "id": "b8d81b3d-f348-4d36-a282-33da8908f0fb",
      "name": "ASLPM",
      "category_key": "professional-services",
      "url": "https://www.aslpm.com/wp-content/uploads/2023/09/ASLPM-logo.jpg"
    },
    {
      "id": "ef28eeab-6fa6-4820-8a1b-02e55cc83d04",
      "name": "B & K Financial - Accounting & Tax Services",
      "category_key": "professional-services",
      "url": "https://www.bkfinancial.org/assets/images/bk-logo.jpg"
    },
    {
      "id": "8df85dee-3c4a-4b4e-9244-266a720d1480",
      "name": "Bonilla Accounting Firm",
      "category_key": "professional-services",
      "url": "https://bafaccounting.com/images/logo.png"
    },
    {
      "id": "82a594ac-5919-4cf0-b9e1-09ee3b3a6bb4",
      "name": "Braff Law Car Accident Personal Injury Lawyers",
      "category_key": "professional-services",
      "url": "https://www.brafflawfirm.com/wp-content/uploads/2021/05/Cosmic_BLA_character.png"
    },
    {
      "id": "e820ff8a-6a03-4767-88cb-b407e7d0c8a3",
      "name": "Consolidated Consultants",
      "category_key": "professional-services",
      "url": "https://group-cc.com/wp-content/uploads/2020/03/logo-2.png"
    },
    {
      "id": "f6be4f2b-d368-4aab-b3e8-fd6b8cf58921",
      "name": "Cycles Consulting",
      "category_key": "professional-services",
      "url": "https://cyclescon.com/logo.jpg"
    },
    {
      "id": "2e14b4c4-17f8-4fd5-881c-076c89409f1a",
      "name": "David P. Shapiro Criminal Defense Attorneys",
      "category_key": "professional-services",
      "url": "https://s3-media0.fl.yelpcdn.com/bphoto/ZD1gyR_gT3XE8bBP5yuzLw/o.jpg"
    },
    {
      "id": "7d0c39fd-2645-4627-af2c-c080461a3703",
      "name": "De Santis Law Center, APC",
      "category_key": "professional-services",
      "url": "https://www.desantislawcenter.com/assets/images/logo.jpg"
    },
    {
      "id": "485fd5ab-4713-4b3e-90b0-27e317ed9c1e",
      "name": "DM Defense Consulting",
      "category_key": "professional-services",
      "url": "http://www.dmdc-inc.com/image.jpg"
    },
    {
      "id": "b99d110a-1970-4345-9817-3a1a709005fe",
      "name": "Doan - Chapter 7 - 13 - Bankruptcy Attorney San Diego",
      "category_key": "professional-services",
      "url": "https://www.bcgsearch.com/photos/KrUGH-Doan-Law-Firm.jpg"
    },
    {
      "id": "1e2ced33-d97f-41bd-a1bb-ad0f9a242f2a",
      "name": "Durvis Accounting Bookkeeping & Tax",
      "category_key": "professional-services",
      "url": "https://s3-media0.fl.yelpcdn.com/bphoto/6eX9H9s3Uq5lIUz41S-tvr/o.jpg"
    },
    {
      "id": "c76c52b5-9d0a-4748-adf3-30cdb063b933",
      "name": "Equity Legal LLP of Chula Vista",
      "category_key": "professional-services",
      "url": "https://www.equitylegalllp.com/wp-content/uploads/2023/02/Equity-Legal-LLP-banner.jpg"
    },
    {
      "id": "733325b7-427d-43e9-9841-37589ac0b0d4",
      "name": "Estolano Law",
      "category_key": "professional-services",
      "url": "https://estolanolaw.com/ocl-assets/uploads/sites/29/2017/06/logo-estolano-law.png"
    },
    {
      "id": "fb0c0827-2e3a-4e30-84d4-0ac777ceb046",
      "name": "Genesis Family Law",
      "category_key": "professional-services",
      "url": "https://genesisfamilylaw.com/wp-content/uploads/2020/05/Genesis-Family-Law-and-Divorce-Lawyers.png"
    },
    {
      "id": "bd4ff0f9-d343-412b-8814-08dcfc5b3c4e",
      "name": "Herrera Law Firm",
      "category_key": "professional-services",
      "url": "https://www.herreralaw.com/images/lawfirm-logo.png"
    },
    {
      "id": "8e96bc00-6861-4739-9562-27b16d534d4d",
      "name": "Ibarra Carrillo Soto CPAs + Advisors",
      "category_key": "professional-services",
      "url": "https://www.yelp.com/bphoto/q9mC3Vn7_CODEC2V7uNLDQ/o.jpg"
    },
    {
      "id": "a207d8ac-a2fa-4b0a-8938-e39ba6bf3ed5",
      "name": "Kingston & Kingston",
      "category_key": "professional-services",
      "url": "https://1000logos.net/wp-content/uploads/2021/04/Kingston-Logo.png"
    },
    {
      "id": "e23d250f-33d6-4add-b2ef-43b9b9624d64",
      "name": "Launch CPA",
      "category_key": "professional-services",
      "url": "https://launchcpa.com/wp-content/uploads/2020/05/Launch_CPA_Logo.png"
    },
    {
      "id": "c324ac11-0385-4716-86b5-ddfb8e892904",
      "name": "Law Office of George Siddell: Personal Injury, Criminal Defense, Immigration, Car Accidents, DUI, Bankruptcy",
      "category_key": "professional-services",
      "url": "https://www.georgesiddell.com/wp-content/uploads/2022/06/George-Siddell-Logo.png"
    },
    {
      "id": "d806fe02-4e64-428f-af45-6e39cdbaf169",
      "name": "Law Office of Leif Kleven",
      "category_key": "professional-services",
      "url": "https://leifkleven.com/wp-content/uploads/2020/01/San-Diego-Personal-Injury-Attorney.png"
    },
    {
      "id": "53421ba0-9fe8-420d-8e58-34ff6bbf0c5b",
      "name": "Love's Accounting San Diego",
      "category_key": "professional-services",
      "url": "https://www.lovesaccounting.com/wp-content/uploads/2022/01/Loves-Accounting-Logo.webp"
    },
    {
      "id": "75e6ca90-ca33-4ddb-a104-2afb8f5bf6b1",
      "name": "Lowell Foster, CPA",
      "category_key": "professional-services",
      "url": "https://cpafoster.com/wp-content/uploads/2020/01/Lowell-Foster.jpg"
    },
    {
      "id": "8edc541f-179a-44db-9416-4d58901fd00d",
      "name": "Management consulting, tax advice - Consultek",
      "category_key": "professional-services",
      "url": "https://www.consultek.com.mx/wp-content/uploads/2018/09/CONSULTEK-1.png"
    },
    {
      "id": "37b6bfea-7c69-49f8-9039-745b70ede975",
      "name": "Montana Consulting",
      "category_key": "professional-services",
      "url": "https://www.montanaconsulting.net/wp-content/uploads/2020/10/MC-Logo-1-300x121.png"
    },
    {
      "id": "280523ce-509e-4533-9ad2-5b410aa3517c",
      "name": "Noble Co.",
      "category_key": "professional-services",
      "url": "https://www.yournobleco.com/images/noble-co-logo.jpg"
    },
    {
      "id": "6487b7c2-edcd-4349-a5cd-f8a779132dad",
      "name": "Odyssey Accounting",
      "category_key": "professional-services",
      "url": "https://www.odysseytaxes.com/images/odyssey-accounting-logo.png"
    },
    {
      "id": "5165a203-dcd2-43b5-89f4-d879410d7be5",
      "name": "Paula Gonzalez Law Office",
      "category_key": "professional-services",
      "url": "https://www.paulagonzalezlaw.com/wp-content/uploads/law-office.jpg"
    },
    {
      "id": "c2d49a84-6531-46e6-886d-a52c4c7a45fe",
      "name": "Peachum Open Source Consulting",
      "category_key": "professional-services",
      "url": "https://www.peachum.org/logo.jpg"
    },
    {
      "id": "f1fb49eb-6e82-49b8-9d72-e301db2b767d",
      "name": "Regal Group CPA",
      "category_key": "professional-services",
      "url": "https://www.regalgroupcpa.com/wp-content/uploads/2021/05/Regal_CPA_logo.png"
    },
    {
      "id": "57cd6cc7-4f5c-4d61-8a63-dd2b44b9aa12",
      "name": "Robert Stewart Digital Marketing",
      "category_key": "professional-services",
      "url": "https://www.robjstewart.com/about/test-image.jpg"
    },
    {
      "id": "6b83b51e-39a6-4bf6-aec4-5c79c5a97a94",
      "name": "RobinStar Tax Consultants, Inc.",
      "category_key": "professional-services",
      "url": "https://robinstartax.com/wp-content/uploads/2020/11/logo.png"
    },
    {
      "id": "91b6bb6e-fadc-4eee-b47b-9c8191901cec",
      "name": "San Diego Business Advisors",
      "category_key": "professional-services",
      "url": "https://www.sdbizadv.com/assets/images/logo.png"
    },
    {
      "id": "404ccd74-ef8f-4c9c-8f18-010a302c8cc0",
      "name": "San Diego CPA",
      "category_key": "professional-services",
      "url": "https://sandiegocpa.com/wp-content/uploads/2023/01/CPA-Image.jpg"
    },
    {
      "id": "e2d67c79-0de4-4be9-92a4-be4544c000cb",
      "name": "San Diego Tax Services",
      "category_key": "professional-services",
      "url": "https://www.utctaxpros.com/images/home_tax.jpg"
    },
    {
      "id": "993800d0-1458-4c86-8fb8-ada4f62ebc57",
      "name": "San Diego Taxman",
      "category_key": "professional-services",
      "url": "https://sandiegotaxman.com/image.jpg"
    },
    {
      "id": "f489f2e4-aa88-4c0e-975d-16a52ab00f1f",
      "name": "San Diego, CPA A Professional Tax & Accountancy Corporation",
      "category_key": "professional-services",
      "url": "https://www.cpapracticeadvisor.com/media/__sized__/2019/12/CPA_Horizons_Firmresize-1547x1031-thumbnail-130x130-75.jpg"
    },
    {
      "id": "92a83bc2-0946-43ef-aa28-241c456e53d1",
      "name": "Schwartz & Schwartz",
      "category_key": "professional-services",
      "url": "https://www.schwartzaccountants.com/wp-content/uploads/2022/04/accounting-team.jpg"
    },
    {
      "id": "26cfee04-7258-4094-a82a-b7e836f50987",
      "name": "Taxlana",
      "category_key": "professional-services",
      "url": "https://www.taxlana.com/wp-content/uploads/logo.jpg"
    },
    {
      "id": "79285a8c-0507-4615-a11e-53d05999375a",
      "name": "The Nielsen Firm, Abogados de Accidentes Near Me",
      "category_key": "professional-services",
      "url": "https://s3-media0.fl.yelpcdn.com/bphoto/1_0G_POxR9rZ1tDeG7MkwA/o.jpg"
    },
    {
      "id": "c5b0cdfe-02cb-4d07-b8db-34160401e7af",
      "name": "6 Grados Coffee",
      "category_key": "restaurants-cafes",
      "url": "https://lh3.googleusercontent.com/gps-cs-s/AC9h4npCxGtqNOgZxWdm_HPSit5yow06eDnnVzZgTfTdkCalmAqHMg1VMLIX_8qjPVnYjrXx9tXjIOogrJbRwPlunU7jURDgglMU791S9S6pHi_AmmibFhtTTITW89Q5neT2krb72fmDWQ=w408-h306-k-no"
    },
    {
      "id": "7b4ffefa-c894-439c-84ec-8a65584aabfc",
      "name": "Applebee's Grill + Bar",
      "category_key": "restaurants-cafes",
      "url": "https://www.ezlocal.com/upload/photos/d700b66c/applebees-in-streetsboro-oh-6.jpg"
    },
    {
      "id": "5df80120-3a9b-432c-8fa5-64beb6348fb8",
      "name": "Better Buzz Coffee Bonita",
      "category_key": "restaurants-cafes",
      "url": "https://lh3.googleusercontent.com/gps-cs-s/AC9h4nqCFYcLcq2_lAJTMgnA-pnhEZ8bd6v8vZWr5WScKf_H60z78estZDkphLPRaSBuREy_GP9k0dx52TkwCJuw4ZzFGpGPLPAkE6bB5SAQvnu3JTVSOVhMP8lgGLhkA4kXYlYXtePB2N-qZuDk=w426-h240-k-no"
    },
    {
      "id": "e5f1d11f-c277-49ff-a522-9e899ed630c2",
      "name": "BJ's Restaurant & Brewhouse",
      "category_key": "restaurants-cafes",
      "url": "https://seeklogo.com/images/B/bjs-restaurant-brewhouse-logo-81DEA867B4-seeklogo.com.png"
    },
    {
      "id": "c6378247-1522-4c05-b852-24f12618d096",
      "name": "Broken Yolk Cafe",
      "category_key": "restaurants-cafes",
      "url": "https://www.thebrokenyolkcafe.com/wp-content/uploads/2021/06/Sunrise.jpg"
    },
    {
      "id": "48234c5f-f05f-40f0-aca5-c9ce4b07978c",
      "name": "Camellias - Cocina Brunch",
      "category_key": "restaurants-cafes",
      "url": "https://lh3.googleusercontent.com/gps-cs-s/AC9h4npLzABYu7att2uSluXLI-wATzEs9eQR4S2rwyERhn7aVRb5UqsPF27vdNV7WYOnET29rmXJDcNoPLBSwPcXLGpgyqeDVjjuawZza3kU2Tw2-pa8xbxBwSkUgWy1Cev1T0aw8u_5zjphNf7Y=w408-h544-k-no"
    },
    {
      "id": "e6efa014-6589-4986-9137-73d45967bddd",
      "name": "Caribe Restaurant & Bar",
      "category_key": "restaurants-cafes",
      "url": "https://lh3.googleusercontent.com/gps-cs-s/AC9h4nq5KbOC05hu7AcFdUiuJlq4MP44URqgvonu1RIYrGJp-nr05EmNYtnNA_r8YUTQx6azz68BUianiAC8EYmeLndihhb3UFHffInOijfL73p6LaUuYBJLlP-fD5isnzicF-ovHKF20A=w408-h306-k-no"
    },
    {
      "id": "8dc340b6-a01d-4f0a-8126-9cced629cb0e",
      "name": "Chief's Da Crab Shack",
      "category_key": "restaurants-cafes",
      "url": "https://lh3.googleusercontent.com/gps-cs-s/AC9h4no7nYWXXuoVJBsWDusx1jHW2NLGlsv5PRMKldXs_ULgzQMLl-5yvcakLORdZ6tmoum-RUFa1dFogByI3xPNde7cv_0tyMNrWL_7rQv2YsWRMez_zbEpN_voGjg4FxEfMRetT5dGIw=w408-h544-k-no"
    },
    {
      "id": "717183b9-e9c9-4826-b178-4b2ced352c28",
      "name": "Colima's Mexican Foods",
      "category_key": "restaurants-cafes",
      "url": "https://lh3.googleusercontent.com/gps-cs-s/AC9h4npRluXP0hyCB5fF9qV7fy-o-OgWmMjO577MLLz7r2ZVg-lSyh7MzEho_geJz1hH8x1VkTmKOBSu-A8qsQ9S77B4MVvPN2LPbgnqoIpRCTqgV_2cMZZ0FqGCIC2j-cMlLSeYdkYkyw"
    },
    {
      "id": "94e95fc0-bfcc-4b9e-a075-0c21ebc15113",
      "name": "Denny's Restaurant",
      "category_key": "restaurants-cafes",
      "url": "https://upload.wikimedia.org/wikipedia/commons/9/90/Denny%27s_Restaurant_in_Brooklyn_NY.jpg"
    },
    {
      "id": "872f9062-7baf-42be-b12b-8ce37b3f9dfa",
      "name": "Dolche cafe/ Mexifood",
      "category_key": "restaurants-cafes",
      "url": "https://lh3.googleusercontent.com/gps-cs-s/AC9h4npJCs1MR4fYHgHDYsiHbPhfZpaERz3rYPASbI6vOBZBcXJyRdtOzvDtGu-GLIGusJ6jj95PHknVePY9J6kjTde9x5O1iEN-dlDeQ_iW3-VcVVQVDe5neGFBEuF-XLi7Du2Fr2Kl=w408-h306-k-no"
    },
    {
      "id": "dd6204ca-7ccf-4096-9e76-929000a52505",
      "name": "Donny's Cafe",
      "category_key": "restaurants-cafes",
      "url": "https://lh3.googleusercontent.com/gps-cs-s/AC9h4npydGnyfsArvpBzodWs5Ae9d68e5Ou1fw8A6RV-qe7nZue0Hl3xf1wq18rfsbfdffQHta5LpNywXVaNrUCCC4XQSNc0VVrdeAzESM6VxdAwRqiaL6aNFldpe5Gjw6rNNqItY83N=w408-h306-k-no"
    },
    {
      "id": "acdfff0a-baac-4373-89e6-593657bab6e5",
      "name": "El Pollo Grill - Bonita",
      "category_key": "restaurants-cafes",
      "url": "https://lh3.googleusercontent.com/gps-cs-s/AC9h4nqF7rr95oH5w9XQk2gBGoEwKthVHnAnN8EM2ob7_sOWANxCz1xnteZDdi7UT4f1sz9ZJqGttzC4oLcla5bhvkgtpg_xOza6KklCy8McpdIoCbve-CQlu-kD5bORHqV-rz64Y8Vc=w426-h240-k-no"
    },
    {
      "id": "f00b6e55-8b2e-4f30-9f27-5d14ade5a826",
      "name": "Franco's Flapjack Family Restaurant",
      "category_key": "restaurants-cafes",
      "url": "https://lh3.googleusercontent.com/gps-cs-s/AC9h4noYNThSrXkcxeDb9oQARjgPktn-Y3x9j2j3WS9d7HV0zQEVVzj0xGYHJnThjSuyseEm3DLOSg4TetOwuhfbeglWru9q5PWAebcxnDpWCEmsJwGVQIk8Lvl9QJE7zHxc_rDhPGLA=w426-h240-k-no"
    },
    {
      "id": "0df63a34-a4de-4f85-9bab-86c9a8f11a0a",
      "name": "Fresheria - Bonita",
      "category_key": "restaurants-cafes",
      "url": "https://lh3.googleusercontent.com/gps-cs-s/AC9h4nqVDJX6RFysmdsL2lPpYe4o-U-Gxkjy95-l41nUWn2lXUhY9Y93Lubxdk-7y0-E3ldziWWbFaKRttaiN0JQnrVbfXxd7YlS6aNe-SQFXrtX3opX5JFzNrI1C7tv61NpLZqq6-eN=w493-h240-k-no"
    },
    {
      "id": "a0d225ff-a000-4a5e-8632-c09669cc11ce",
      "name": "Frutas 100 Natural",
      "category_key": "restaurants-cafes",
      "url": "https://lh3.googleusercontent.com/gps-cs-s/AC9h4npV5JpsjgeHMrTlNYurBq7pPMnkGz-wWM7pmAn2A5Za71utbpis9fFjo69mUmd7hn851H22viYa-sUX-w5fgTf8UeyC8oWWt1wfIk66mq9Ag15FCXIeiZ6K5t98RUE2F6X4aCzYAQ=w506-h240-k-no"
    },
    {
      "id": "f37f648f-45db-46e8-a121-beb807413e16",
      "name": "GK Grill Mongolian Taste",
      "category_key": "restaurants-cafes",
      "url": "https://lh3.googleusercontent.com/gps-cs-s/AC9h4noIMVZAQWwR09354MCcfM5u3XbLTZaEBU_nmv-TIJb9sD3jZ2MC8RB1YJjIPaZd_le46a0rj4IxChPza7sW1Cu_-X10yJTELNV_EwOEAe9AJG1gD03KNJgrdxwa-RLcZvsJXm58=w408-h306-k-no"
    },
    {
      "id": "96401196-9378-406a-90d0-e2c4155b21e4",
      "name": "Graciela's Taco Shop",
      "category_key": "restaurants-cafes",
      "url": "https://lh3.googleusercontent.com/gps-cs-s/AC9h4nq25pJUdpJyAV9emQYEZNR9aQ2TqxRvot38KdFLALs1assSFc41_AMjlfX3fF0g2YFrzDFC_-dqUwWUsMG_KgvM7Z3yToCoD4ZghrJjtjiq63Bwi3MOxKlXyy0It_OGpd2P-eJK2w=w408-h306-k-no"
    },
    {
      "id": "234f32e6-2de7-402d-b4f0-1cb2e47a0241",
      "name": "Italianissimo Trattoria",
      "category_key": "restaurants-cafes",
      "url": "https://lh3.googleusercontent.com/gps-cs-s/AC9h4np1zbmKw-86wDGUU2CKXSD8iRuHdFEngFx6iAKQWtDBAgp0-5wfBZd2VeO7Kb7iwH0cl-UWe7QyF_fliWN45_Ds7DEGV2_54hM42lzFLwdjnm8rX25ZQ9tGkLKU3DPDoa3SgqFX=w453-h240-k-no"
    },
    {
      "id": "08a2e331-fd95-4883-9986-49462690ed7a",
      "name": "Jalisco Cafe",
      "category_key": "restaurants-cafes",
      "url": "https://lh3.googleusercontent.com/gps-cs-s/AC9h4noVIH65ZIoBFNhs6M1E3fv9TTy3or82dMyW1K8iXwm4UITAs06JRXmYolcUuARDyNW3Aipbc_MU4tR02jiiitoXQfBgJVNC9fMP2fuoEsm-JXGG7DON8aF4Iac3Oy__foMPtBG4=w408-h306-k-no"
    },
    {
      "id": "aedce2d4-0001-4675-80c2-afc6d3ce87e3",
      "name": "Jibaritos de la Isla",
      "category_key": "restaurants-cafes",
      "url": "https://lh3.googleusercontent.com/gps-cs-s/AC9h4npSWW0UYcO_5LmmSBOs_mAk8JmD1Yti4xYHwL9uReFtHkQJfE6MVxVJl9HL5Uf_ogGDlCgstMjMxo3gaSyU5nl9ywotWa7f8dKA-bpQkDaG9VyoJvaTugIjb0MbbMk9Y4M7oLs=w408-h307-k-no"
    },
    {
      "id": "7f5cee3c-ff45-474c-a7d2-0c6f8f415f2b",
      "name": "KABOB SHACK - BROADWAY",
      "category_key": "restaurants-cafes",
      "url": "https://lh3.googleusercontent.com/gps-cs-s/AC9h4npI71-ndBcGZwAv7zG0r8an1hECg7MSDofraTqg1-XromcLkPFRa8mKrBoEbXqjffQ728i5RO6n3xBzpkBW71ZsBuoG8jHb4G_GJdGgwsoP9nt5UWfnpuLfgAPrqkINdSbuS3ot=w408-h544-k-no"
    },
    {
      "id": "185f884a-6de5-4ad0-95ae-6b653b4884d1",
      "name": "Karina's Mexican Seafood",
      "category_key": "restaurants-cafes",
      "url": "https://lh3.googleusercontent.com/gps-cs-s/AC9h4noPndMmHQbR0jTIaTdVwAGXMidxmGLUG7t5XJhjBk5HBkrgQLeL5_rRdWJzUapac5gxhq3O9qDGOnxFCE4v7PEHi-T9aJptvvb1-P6etbhdGG53YBVEGCgtAtfx4sRzax-rbtKw=w408-h306-k-no"
    },
    {
      "id": "0ac2cb7d-f040-49c7-970b-a55318c65138",
      "name": "Lil Alex BBQ",
      "category_key": "restaurants-cafes",
      "url": "https://www.restaurantji.com/sites/default/files/styles/480x400/public/restaurant/thumb/2025/25/Lil-Alex-BBQ-thumb.jpg"
    },
    {
      "id": "aa9ea2aa-4978-4ef4-8b4f-f5d20d393aa2",
      "name": "Lolita's Mexican Food",
      "category_key": "restaurants-cafes",
      "url": "https://lh3.googleusercontent.com/gps-cs-s/AC9h4no3yZzLd73Im2GAwNcshz-cv81Dq8jdu9XUiCxfU0oNUlk-_W0Y42olFHo8TMLKKO7qiCSUdX9R9R_agishaqPpDWSMxyA32kkY5kkH0W3gHLYeM4xeDVVcW47iE6JKcjINi_etuA=w408-h306-k-no"
    },
    {
      "id": "e85a1d74-fae5-4cae-a7d1-bd430d17318d",
      "name": "Manna BBQ",
      "category_key": "restaurants-cafes",
      "url": "https://mannabbq.com/images/manna_logo.png"
    },
    {
      "id": "c5baacb9-52ea-4ac8-9415-d89b8f4d795f",
      "name": "Maple Tree Coffee",
      "category_key": "restaurants-cafes",
      "url": "https://lh3.googleusercontent.com/gps-cs-s/AC9h4nqvULbsmVXf62ffRM9waTkdlza-hBQkGYsjF73GhECeVoZlHv1igiIGN3-5Of8CC-0VQbXheifqDcMOlN9ZNUHIaabYOZ6reX4WSBFmzlU0ViTPYJmAMFnC-PXjoHNnDN9SCHA=w408-h724-k-no"
    },
    {
      "id": "20540155-c955-46e2-86e2-c97d2cb81a97",
      "name": "Monterrey Ribeye Burgers",
      "category_key": "restaurants-cafes",
      "url": "https://lh3.googleusercontent.com/gps-cs-s/AC9h4npUkkRfZy1fQCDzUmb-i440eJArsO6iwm8UiQf-v4sz_1WS-VFC1CmQtSMLdBt7zQJIMHPeLjNiM9WDSTTxaI50b88rPZsfLHilZp5qvns3GfumpjLIyzKcJlAaIo1HkzHrpP1n=w408-h306-k-no"
    },
    {
      "id": "170a929b-dc16-457e-abec-a798250823ca",
      "name": "Murrieta's Mexican Restaurant",
      "category_key": "restaurants-cafes",
      "url": "https://lh3.googleusercontent.com/gps-cs-s/AC9h4npvSQ_gKJhyq31tG9fh4mn3ZhwseUdW5T7YX-w7KJgg_TtKasNVxMMOGBzCT3niFXJj58CPav8gMlCK61F-yX02ba5a-dlJzAvXlxpMIwgoip1bDpLShc84Yzhg8rVMx-i6kZwe5g=w426-h240-k-no"
    },
    {
      "id": "fc65159c-039e-414e-98da-8e3c7034ce6a",
      "name": "Panda Express",
      "category_key": "restaurants-cafes",
      "url": "https://www.stickpng.com/assets/images/5842996fa6515b1e0ad75add.png"
    },
    {
      "id": "8a67733e-730a-4ba9-8d46-56d53182931d",
      "name": "Por Vida",
      "category_key": "restaurants-cafes",
      "url": "https://lh3.googleusercontent.com/gps-cs-s/AC9h4nqLrdLff3RrjaRbaVNDSYfOv2ALQUDhlSE_lKbj0uJ2wsfCJPzBOcaJlTvmhG17nte-_HSju5di3-5KODKhtC7VaiwFZeGqn_ynNZnHcZlPuINaHGzexOWBvzyaXdMW95GscD-DLw=w408-h306-k-no"
    },
    {
      "id": "7dfc4cba-b39d-49b4-a097-07bb9e7af39e",
      "name": "Red Robin Gourmet Burgers and Brews",
      "category_key": "restaurants-cafes",
      "url": "https://upload.wikimedia.org/wikipedia/commons/a/a6/Red_Robin_Bacon_Cheeseburger.jpg"
    },
    {
      "id": "b487ec57-c9e9-4cb4-9741-ec40c35dbb9d",
      "name": "Sammy's Restaurant & Bar",
      "category_key": "restaurants-cafes",
      "url": "https://lh3.googleusercontent.com/gps-cs-s/AC9h4npvL-0YDNsX2StXM3mhM-PMgyrd63y3LuMXvLTZouPc-8_r4JL8zLiZlP6CO3-VizDCMJ1B9qHGFvejOgXGEsHEDjQpagev5XIwIlFA2X0g8PmG4YwChsOS7hvdaBJ8gem31Wc46g=w408-h306-k-no"
    },
    {
      "id": "14671850-00ea-4bd0-87da-0f6813fbeb33",
      "name": "Seoul Korean Corndog & Fried Chicken",
      "category_key": "restaurants-cafes",
      "url": "https://lh3.googleusercontent.com/gps-cs-s/AC9h4nrM54e5H8boblQfGEWBWlss2sAcQGTsk63iWwKknDbJdkzzOne4_zTIvS3Gt2DdpvHU-9s1sJCnilSmSXIqJgqjHy6EeZ9L19MQmAzGB3bBU35woY8ZqloWljeF24OGPLiYyoo=w408-h306-k-no"
    },
    {
      "id": "63a8789c-45ee-4688-a7cd-d3f1732cc4e6",
      "name": "Seven Seas Roasting Co. South Park",
      "category_key": "restaurants-cafes",
      "url": "https://lh3.googleusercontent.com/gps-cs-s/AC9h4nqlada62xq4UlwsVD_5H9EuRrVe8W9R-iohWdnQm_0isbhHXePH6V7s1epezxi7rSOrYwcdMlDO1Alr0XRdarVcarEx-WtXQqI3AyN0j6uoaF3sIa4u2FYpGt7uXt1bi3ser3dN=w408-h544-k-no"
    },
    {
      "id": "5f583721-61b4-4ea8-9753-54f024aec218",
      "name": "Starbucks",
      "category_key": "restaurants-cafes",
      "url": "https://lh3.googleusercontent.com/gps-cs-s/AC9h4noRgMAw98JoxkQPye6Jz01p8gFGqiDruxbUzhu4zHx9L5UCcH91mjnHqSRhMcKQpXTo-Sdf6Yer6OPqOC_0SBnZeWBX6ixNFUz_uZ46Wnzd4AY4z033sYi7T6C7E4hEwyg_BQzU=w408-h544-k-no"
    },
    {
      "id": "61854db2-6262-4ef4-be84-5519a505f6a1",
      "name": "Starbucks",
      "category_key": "restaurants-cafes",
      "url": "https://www.starbucks.com/weblx/images/rewards/drinkshttps://www.starbucks.com/weblx/images/rewards/tea.jpg"
    },
    {
      "id": "390cecb4-ca9b-45e2-9a84-eeb5baec09ee",
      "name": "Starbucks",
      "category_key": "restaurants-cafes",
      "url": "https://seeklogo.com/vector-logo/131766/starbucks-coffee"
    },
    {
      "id": "ac922b59-d80d-45fe-b7a7-66ca5beb9307",
      "name": "Taco Machin",
      "category_key": "restaurants-cafes",
      "url": "https://lh3.googleusercontent.com/gps-cs-s/AC9h4nq0QbRPCyWms393cLblYaZW3KRdCGd-d9-rjbun6XJQmvAN1VO5hN8b3CuQzqBppVGbUrdXk1CzkJdSSmrEM_Ca8Y-8-4-pDFwoJnlnXAxrEIFfz0Tuw1lJ9mHkxVuBjtgR7Odd=w408-h306-k-no"
    },
    {
      "id": "427ba8c2-ea88-40e0-9940-32c727a2fad1",
      "name": "Tajima Ramen Plaza Bonita",
      "category_key": "restaurants-cafes",
      "url": "https://lh3.googleusercontent.com/gps-cs-s/AC9h4no7STrDkpXazdgteva4vG6iqAO5esw5zg4jPQpBKC2NLdSFYPy_ODI4d9EZf9MIvwzgTe_xR8Lwl2tvM-p-mmriqL0OXm0ADxV-6pcygo4RGEzEWuQQRuGLOj8XFuW7XAepWwBewA=w408-h544-k-no"
    },
    {
      "id": "2de04383-f5a0-4763-a4cf-b510e3c00927",
      "name": "Tapas Bar",
      "category_key": "restaurants-cafes",
      "url": "https://lh3.googleusercontent.com/gps-cs-s/AC9h4no-12bJ11WymhDbrmuBf0pTv1XlOyRGnWr-oI-4iG1lkjuY14WqYFMFNBXdqxJUrpV-yONMYljcJa41ZGTF2dODp0muxhcJOmYqpFgEfuXP_99-dW2ndI-H8zuv8swhIcr75rg=w408-h292-k-no"
    },
    {
      "id": "28f1f4c8-1837-421a-aa56-f2fa37029b0a",
      "name": "Tapioca Express",
      "category_key": "restaurants-cafes",
      "url": "https://lh3.googleusercontent.com/gps-cs-s/AC9h4nrcHSOLPInAHuhMc9hhyyUTxum_nkS7xbaCuoofTPw1_72-nuzjH9tQBggxaqa4kK3CxAVGBbrWmm-TknjPtqlzQ-Negao_2Q8gxOHaDbNrS3TInXVQtQpfgNjVDq1-WE8p_BObtg=w408-h544-k-no"
    },
    {
      "id": "7b2e7828-8393-4f9c-852f-9da0485bfa40",
      "name": "TG Cafe Chula Vista",
      "category_key": "restaurants-cafes",
      "url": "https://lh3.googleusercontent.com/gps-cs-s/AC9h4nr6sSJqpDeRq_lWihJpskFed4qWWOWZtaOqQ_0wl1LZO1NyUksceVsSaJTcmCT6av7nIed3AGYxZXgAO7r1wfoTqTZ6ftjnfvHFa2Nai7PZ7WAN2UiWw4G3CYeneEZ4f8xcywqwUAlxPR3W=w408-h544-k-no"
    },
    {
      "id": "e996af71-6379-4118-ba79-1212042c1b19",
      "name": "Thai Taste 2",
      "category_key": "restaurants-cafes",
      "url": "https://www.agfg.com.au/uploads/images/listing_img_70140_6c1fe38.jpg"
    },
    {
      "id": "bc98bd44-36a6-4d4e-9114-b4a2d01595a1",
      "name": "The Balboa South",
      "category_key": "restaurants-cafes",
      "url": "https://lh3.googleusercontent.com/gps-cs-s/AC9h4nrcLyEuJeMFSUWSXaZvkKDJNqZqJDuT52yyzU9VZg7xgrflIv9mb28kxaQyWzZhHvgVKcFWXBlpfwouH_nYVpEb7SB6m-Dlsygm4rIxrXWD_CRFc53ZcKMz5ZKTNFStch5PaAFE=w426-h240-k-no"
    },
    {
      "id": "42a29d07-0bc6-4bea-a5ac-50d6a817153a",
      "name": "The Waterfront Grill @ Pier 32 Marina - San Diego",
      "category_key": "restaurants-cafes",
      "url": "https://www.pier32marina.com/wp-content/uploads/2021/02/Waterfront-Grill-Dining-Area.jpg"
    },
    {
      "id": "8af8b746-fdff-49ae-a99d-2fa7d7d4cce5",
      "name": "TJ BURRITO Co.",
      "category_key": "restaurants-cafes",
      "url": "https://s3-media0.fl.yelpcdn.com/bphoto/Da9S0Fj3JK3_-VpQ8B6CqA/o.jpg"
    },
    {
      "id": "2953c6bd-eb26-4a57-a600-24c6a833dfd3",
      "name": "TJ Oyster Bar",
      "category_key": "restaurants-cafes",
      "url": "https://lh3.googleusercontent.com/gps-cs-s/AC9h4nq8wcbjiE-EDBCW2dOfsMyixD2Pqa4TWG8YMwNKKPXoGXN9CemO-8jcvf961_ZImYb_RVO-BuH69zSE2W_euVETryB4KiVnSuusHk0elCuG5SVjii0CRy3ggou6Nusg4lsP7i5y=w408-h296-k-no"
    },
    {
      "id": "0592ea12-b5ff-46b2-98fe-3eb777700f38",
      "name": "Tortas Tj",
      "category_key": "restaurants-cafes",
      "url": "https://lh3.googleusercontent.com/gps-cs-s/AC9h4nq1tkVO1-RU4cWk7PXauFPBUv6sqHm5W4a4v-Pcvx1aGqNcdMhMmCXPEq-bfIdNrsSheKldqrZuXTu_pguN7QuqwQIt_wVKAYTju7xmdX3OacWpDr5AvIXjDX-cAhvyIH84710XBd9veGSV=w535-h240-k-no"
    },
    {
      "id": "ee2078c9-8cf8-4a51-bb80-5a9388d5b19c",
      "name": "Tradewinds Cafe",
      "category_key": "restaurants-cafes",
      "url": "https://lh3.googleusercontent.com/gps-cs-s/AC9h4noxbDHL2ELDrCookZikAQHzcfC58Yh5oLV69YNbXT_e-u8qnnEFQKrBX8hRUX4_dbbS_p8bJqZiDlnSqkzwW8p359CAO3QnmMGkDWTFwBafts3xxSVm5G5N2GOOjGltZZo_JNs=w408-h246-k-no"
    },
    {
      "id": "253f56ba-30e2-4ebd-ae0f-62592b1b2cbc",
      "name": "Urbane Cafe",
      "category_key": "restaurants-cafes",
      "url": "https://lh3.googleusercontent.com/gps-cs-s/AC9h4noVvOth7TFzMpcN5nLa4n0bxwEXic3KniggCZXm72XD0o5ckS-Ka_iX8WBni_mFG-afKGA691GmeL-9hW0wUbTUr68chrBw9AKBvopZxewA_dCG2xsUsniB1svk5hxVTaiN6baYIw=w513-h240-k-no"
    },
    {
      "id": "d871e8ba-fdf7-4cad-b52e-2017b8004dfc",
      "name": "Victorinos Pizzeria",
      "category_key": "restaurants-cafes",
      "url": "https://lh3.googleusercontent.com/gps-cs-s/AC9h4notKTkShPQdbbTlVIq6rgNCS8PMvqPdi2xMyDH6KyW_ioktgrJ8T4B2r-77S_PJFc8-LK32ysWzDWwnoplOQeZ7IVzTvR2QrsYDjJGGakLSwi8oxPI_Mgy9Iff0R111eXT6zDdS=w408-h306-k-no"
    }
  ],
  "skipped": [
    {
      "id": "f6f7012c-1802-4062-b329-d4e30756b864",
      "name": "PRN Physical Therapy - Chula Vista, Fenton St.",
      "category_key": "health-wellness",
      "reason": "Invalid or unusable URL",
      "url": "https://m.facebook.com/PRNptChulaVista/photos/d41d8cd9/4130026190436319"
    },
    {
      "id": "7d16245c-643d-4b60-b7da-6e17116ee825",
      "name": "Stars Salon",
      "category_key": "health-wellness",
      "reason": "Invalid or unusable URL",
      "url": "https://starsalonlasvegas.com/ServiceAndPrice/ShowService"
    },
    {
      "id": "d4e0af50-a9cf-4457-a0c0-89d8570fe99c",
      "name": "Studio 54",
      "category_key": "health-wellness",
      "reason": "Invalid or unusable URL",
      "url": "https://crfashionbook.com/studio-54-anniversary"
    },
    {
      "id": "1b15ed0d-fb7e-4b7b-abcc-e719e95a18a5",
      "name": "Saving On Solar California Solar Power Quotes",
      "category_key": "home-services",
      "reason": "Invalid or unusable URL",
      "url": "(empty)"
    },
    {
      "id": "bbb8c295-a0f7-4612-b7f4-11ec0bf8a210",
      "name": "Abbo Tax CPA",
      "category_key": "professional-services",
      "reason": "Invalid or unusable URL",
      "url": "https://www.google.com/search?tbm=isch&q=Abbo+Tax+CPA+logo"
    },
    {
      "id": "ca7ecd61-7e7f-45fd-af85-7b48352242d9",
      "name": "American Profit Consulting",
      "category_key": "professional-services",
      "reason": "Invalid or unusable URL",
      "url": "https://www.google.com/search?tbm=isch&q=American+Profit+Consulting+logo"
    },
    {
      "id": "2da0ab71-6ede-4995-bcb2-65593e626c94",
      "name": "American Veteran Consulting",
      "category_key": "professional-services",
      "reason": "Invalid or unusable URL",
      "url": "https://www.google.com/search?tbm=isch&q=American+Veteran+Consulting+logo"
    },
    {
      "id": "9dcd5e4c-c060-48f2-819c-02b6abd73378",
      "name": "Araceli C. Rivera, CPA",
      "category_key": "professional-services",
      "reason": "Invalid or unusable URL",
      "url": "(empty)"
    },
    {
      "id": "0d6b7850-798b-41df-8ef2-95c648e9170a",
      "name": "Blasquez Consulting Services",
      "category_key": "professional-services",
      "reason": "Invalid or unusable URL",
      "url": "https://www.google.com/search?tbm=isch&q=Blasquez+Consulting+Services+logo"
    },
    {
      "id": "16d61138-4b72-4f17-b2ef-8456b3132519",
      "name": "Bonita Valley Tax & Bookkeeping",
      "category_key": "professional-services",
      "reason": "Invalid or unusable URL",
      "url": "https://www.dnb.com/business-directory/company-profiles.bonita_valley_tax__bookkeeping_service.e3424dc0708bda75c7472bab96c317dd.html"
    },
    {
      "id": "7973f1c4-a4f8-4d69-ab63-6f1391f00955",
      "name": "Broaden Law LLP",
      "category_key": "professional-services",
      "reason": "Invalid or unusable URL",
      "url": "https://www.yelp.com/biz_photos/broaden-law-chula-vista-4"
    },
    {
      "id": "2ce56b7b-5b56-48e5-b713-70efe506904f",
      "name": "Castaneda Tax & Financial",
      "category_key": "professional-services",
      "reason": "Invalid or unusable URL",
      "url": "https://www.castanedasfinancialsolutions.com/"
    },
    {
      "id": "1d209ed7-40a2-41d5-9690-2784f2934b4a",
      "name": "CHULA VISTA CPA | TAX CPA",
      "category_key": "professional-services",
      "reason": "Invalid or unusable URL",
      "url": "https://www.google.com/search?tbm=isch&q=CHULA+VISTA+CPA+%7C+TAX+CPA+logo"
    },
    {
      "id": "dcda5126-8643-448c-88e8-eb9c8dcac328",
      "name": "Correa Law Firm, APC",
      "category_key": "professional-services",
      "reason": "Invalid or unusable URL",
      "url": "https://www.google.com/search?tbm=isch&q=Correa+Law+Firm,+APC+logo"
    },
    {
      "id": "84e56e43-671c-4bad-b81c-7fa3fbbfa6c8",
      "name": "Domestic Violence Attorney San Diego",
      "category_key": "professional-services",
      "reason": "Invalid or unusable URL",
      "url": "https://www.google.com/search?tbm=isch&q=Domestic+Violence+Attorney+San+Diego+logo"
    },
    {
      "id": "1854c0c7-e957-4d08-91ed-58129955851d",
      "name": "EJ's IT Consulting",
      "category_key": "professional-services",
      "reason": "Invalid or unusable URL",
      "url": "https://www.google.com/search?tbm=isch&q=EJ's+IT+Consulting+logo"
    },
    {
      "id": "79867a77-82d3-42f7-b482-92e05501ab03",
      "name": "Elite Criminal Defense - Chula Vista",
      "category_key": "professional-services",
      "reason": "Invalid or unusable URL",
      "url": "https://www.google.com/search?tbm=isch&q=Elite+Criminal+Defense+-+Chula+Vista+logo"
    },
    {
      "id": "53f8ae34-fd17-4bdc-802b-fd51f21c067d",
      "name": "Fall Consulting Services",
      "category_key": "professional-services",
      "reason": "Invalid or unusable URL",
      "url": "(empty)"
    },
    {
      "id": "818434c9-6c03-4328-81e2-42c1d4f252f1",
      "name": "Felix and Associates, LLC - Water Resource Management Consulting",
      "category_key": "professional-services",
      "reason": "Invalid or unusable URL",
      "url": "https://www.google.com/search?tbm=isch&q=Felix+and+Associates,+LLC+-+Water+Resource+Management+Consulting+logo"
    },
    {
      "id": "61ac3fb7-7fae-43d2-b899-fe06998090c9",
      "name": "Flat Rate Divorce",
      "category_key": "professional-services",
      "reason": "Invalid or unusable URL",
      "url": "https://www.google.com/search?tbm=isch&q=Flat+Rate+Divorce+logo"
    },
    {
      "id": "1d62200c-c74a-4c24-898e-1248469a16f6",
      "name": "Gatto Pope & Walwick, LLP Certified Public Accountants",
      "category_key": "professional-services",
      "reason": "Invalid or unusable URL",
      "url": "(empty)"
    },
    {
      "id": "2181b16a-0679-482c-ae26-cd7c6c42f4ae",
      "name": "Golden & Cardona-Loya, LLP",
      "category_key": "professional-services",
      "reason": "Invalid or unusable URL",
      "url": "https://www.google.com/search?tbm=isch&q=Golden+%26+Cardona-Loya+LLP+logo"
    },
    {
      "id": "e07c8c51-735d-451f-9b16-28fedf657195",
      "name": "Green & Green LLP, Attorneys at Law",
      "category_key": "professional-services",
      "reason": "Invalid or unusable URL",
      "url": "(empty)"
    },
    {
      "id": "8efcc687-602d-477e-89ae-264234eac3f7",
      "name": "Greg Martinez CPA, Inc.",
      "category_key": "professional-services",
      "reason": "Invalid or unusable URL",
      "url": "https://m.facebook.com/GregMartinezCPA/photos/d41d8cd9/1006473891483459/"
    },
    {
      "id": "28d4fcde-ff09-474c-b64a-2c20f3f111d5",
      "name": "Guzman Legal",
      "category_key": "professional-services",
      "reason": "Invalid or unusable URL",
      "url": "https://guzman.legal/"
    },
    {
      "id": "62bc7dc7-e10c-4c75-bfbc-d060960944e3",
      "name": "H&R Block",
      "category_key": "professional-services",
      "reason": "Invalid or unusable URL",
      "url": "https://myschoolportal.net/blog/download/hr-block-logo/"
    },
    {
      "id": "6c1c9c78-b0a6-4685-bab8-8f99523ee73d",
      "name": "Haskins & Associates",
      "category_key": "professional-services",
      "reason": "Invalid or unusable URL",
      "url": "(empty)"
    },
    {
      "id": "1ecc8e2f-666c-438e-84f9-5e432e6dd471",
      "name": "higi",
      "category_key": "professional-services",
      "reason": "Invalid or unusable URL",
      "url": "https://www.higi.com/"
    },
    {
      "id": "7af75fc3-b809-4e83-b191-07e0b8042641",
      "name": "JAC Law Office",
      "category_key": "professional-services",
      "reason": "Invalid or unusable URL",
      "url": "https://www.google.com/search?tbm=isch&q=JAC+Law+Office+logo"
    },
    {
      "id": "31612005-47e3-4ccf-aed0-678b80d8e826",
      "name": "Jb Consultants",
      "category_key": "professional-services",
      "reason": "Invalid or unusable URL",
      "url": "https://www.google.com/search?tbm=isch&q=Jb+Consultants+logo"
    },
    {
      "id": "8bcee09b-9dd0-4ece-93e0-1afda1597a8b",
      "name": "JRG TAX SERVICE",
      "category_key": "professional-services",
      "reason": "Invalid or unusable URL",
      "url": "(empty)"
    },
    {
      "id": "f52eace5-0ea3-4061-bdbf-6ff05822606a",
      "name": "Kash Legal Group - Chula Vista Personal Injury and Accident Lawyers",
      "category_key": "professional-services",
      "reason": "Invalid or unusable URL",
      "url": "https://www.google.com/search?tbm=isch&q=Kash+Legal+Group+-+Chula+Vista+Personal+Injury+and+Accident+Lawyers+logo"
    },
    {
      "id": "420a9319-e57c-4b94-8b1c-1750e89a7ef2",
      "name": "Koala Financial and Bonita Tax Service",
      "category_key": "professional-services",
      "reason": "Invalid or unusable URL",
      "url": "https://www.google.com/search?tbm=isch&q=Koala+Financial+and+Bonita+Tax+Service+logo"
    },
    {
      "id": "e75208f1-417a-4c6f-95ad-998070b34a95",
      "name": "Koala Financial and Bonita Tax Service",
      "category_key": "professional-services",
      "reason": "Invalid or unusable URL",
      "url": "https://www.google.com/search?tbm=isch&q=Koala+Financial+and+Bonita+Tax+Service+logo"
    },
    {
      "id": "75eb26f9-373e-4b09-91a2-ac2f3304bfae",
      "name": "Law Office of Carlos C. Ruan",
      "category_key": "professional-services",
      "reason": "Invalid or unusable URL",
      "url": "https://www.linkedin.com/company/law-office-of-carlos-c-ruan"
    },
    {
      "id": "64b29197-101e-4098-bb71-080aff7459b0",
      "name": "Law Office of Eduardo B. Alejo",
      "category_key": "professional-services",
      "reason": "Invalid or unusable URL",
      "url": "https://www.google.com/search?tbm=isch&q=Law+Office+of+Eduardo+B.+Alejo+logo"
    },
    {
      "id": "722360b0-ae23-4e02-aeb0-9ad617a08220",
      "name": "Law Office of Victor Mordey",
      "category_key": "professional-services",
      "reason": "Invalid or unusable URL",
      "url": "(empty)"
    },
    {
      "id": "c848f539-194d-4fcf-9b49-b3fae576768d",
      "name": "Law Offices of Samuel Sue",
      "category_key": "professional-services",
      "reason": "Invalid or unusable URL",
      "url": "(empty)"
    },
    {
      "id": "24650fa7-7d1a-4909-9221-8fd91d2a9aec",
      "name": "Linda Catalina, CPA",
      "category_key": "professional-services",
      "reason": "Invalid or unusable URL",
      "url": "https://www.google.com/search?tbm=isch&q=Linda+Catalina%2C+CPA+logo"
    },
    {
      "id": "d5527968-bae4-4e7d-b811-a3930ac0f0f0",
      "name": "Lyle W Hunter Financial Services",
      "category_key": "professional-services",
      "reason": "Invalid or unusable URL",
      "url": "(empty)"
    },
    {
      "id": "89fe15d8-89f2-4868-b146-13d647896726",
      "name": "M.W. Orlando CPA, Inc.",
      "category_key": "professional-services",
      "reason": "Invalid or unusable URL",
      "url": "I couldn't find a direct image URL that ends in .jpg, .png, .webp, or .jpeg from the official website, LinkedIn, or Facebook presence of M.W. Orlando CPA, Inc."
    },
    {
      "id": "a72daf43-1fda-4ca3-8cd3-6e1f82cb97fa",
      "name": "Marin Tax Service",
      "category_key": "professional-services",
      "reason": "Invalid or unusable URL",
      "url": "https://m.facebook.com/photo.php?fbid=1040228014789678"
    },
    {
      "id": "61b3f1de-d7d6-463b-ba20-bbb45bbbefee",
      "name": "MEG International Counsel, PC",
      "category_key": "professional-services",
      "reason": "Invalid or unusable URL",
      "url": "https://www.google.com/search?tbm=isch&q=MEG+International+Counsel+PC+logo"
    },
    {
      "id": "8d4b5868-9107-40d0-984c-8de337e9d319",
      "name": "Mission Personal Injury Lawyers Chula Vista",
      "category_key": "professional-services",
      "reason": "Invalid or unusable URL",
      "url": "https://images.unsplash.com/photo-1545239351-1141bd82e8a6?ixid=MnwyNzY5MDN8MHwxfGFsbHx8fHx8fHx8fDE2NDkxOTE3MjE&ixlib=rb-1.2.1"
    },
    {
      "id": "fb358303-96c3-4e44-8c07-c2b78e87f87c",
      "name": "Paul Anderson - CPA and Bookkeeping Firm",
      "category_key": "professional-services",
      "reason": "Invalid or unusable URL",
      "url": "https://www.google.com/search?tbm=isch&q=Paul+Anderson+-+CPA+and+Bookkeeping+Firm+logo"
    },
    {
      "id": "8910ae55-8dae-48d7-abec-c80c27d17052",
      "name": "PKF San Diego, LLP",
      "category_key": "professional-services",
      "reason": "Invalid or unusable URL",
      "url": "https://www.google.com/search?tbm=isch&q=PKF+San+Diego,+LLP+logo"
    },
    {
      "id": "c68fe6c5-4d10-4549-8d03-eb5679afca84",
      "name": "Premier Taxes",
      "category_key": "professional-services",
      "reason": "Invalid or unusable URL",
      "url": "https://www.google.com/search?tbm=isch&q=Premier+Taxes+logo"
    },
    {
      "id": "ee30d4dc-e579-407c-ac9f-ead51c7ecffb",
      "name": "Prime Business Consulting",
      "category_key": "professional-services",
      "reason": "Invalid or unusable URL",
      "url": "https://www.google.com/search?tbm=isch&q=Prime+Business+Consulting+logo"
    },
    {
      "id": "98d9d5bc-b034-47f1-86b5-a1c853babdf9",
      "name": "Pro Tax Solutions San Diego",
      "category_key": "professional-services",
      "reason": "Invalid or unusable URL",
      "url": "https://protaxllc.com/case-study-county/san-diego"
    },
    {
      "id": "c9e0524a-c811-4dba-a799-dfd5960a9e0f",
      "name": "Profitwise Accounting",
      "category_key": "professional-services",
      "reason": "Invalid or unusable URL",
      "url": "https://brandfetch.com/profitwiseaccounting.com?view=library&library=default&collection=fonts"
    },
    {
      "id": "9c8ee4fc-85a6-412a-b532-232ca34d1b8f",
      "name": "Ramos Law Firm",
      "category_key": "professional-services",
      "reason": "Invalid or unusable URL",
      "url": "https://www.google.com/search?tbm=isch&q=Ramos+Law+Firm+logo"
    },
    {
      "id": "85485b33-1e9f-4e55-b069-67ae902aa0a8",
      "name": "Rancho Consulting",
      "category_key": "professional-services",
      "reason": "Invalid or unusable URL",
      "url": "https://www.google.com/search?tbm=isch&q=Rancho+Consulting+logo"
    },
    {
      "id": "e3887fe4-f96d-41be-9d17-5f0afea6e08d",
      "name": "Red2Tech",
      "category_key": "professional-services",
      "reason": "Invalid or unusable URL",
      "url": "https://www.cloud.xusyou.com/image/RED-6310-2.eZyV/?lang=el"
    },
    {
      "id": "044292b9-8f46-452e-9ba2-e809be5d68af",
      "name": "Reel Fathers Rights APC",
      "category_key": "professional-services",
      "reason": "Invalid or unusable URL",
      "url": "https://www.google.com/search?tbm=isch&q=Reel+Fathers+Rights+APC+logo"
    },
    {
      "id": "3974b9bc-9850-4f66-9e82-c419a2bdac59",
      "name": "San Diego Accident Law Center",
      "category_key": "professional-services",
      "reason": "Invalid or unusable URL",
      "url": "https://www.flickr.com/photos/sandiegoaccidentlawcenter/"
    },
    {
      "id": "192b8274-4192-4bfb-ba13-0a960e5c0f07",
      "name": "San Diego CPA",
      "category_key": "professional-services",
      "reason": "Invalid or unusable URL",
      "url": "https://www.google.com/search?tbm=isch&q=San+Diego+CPA+logo"
    },
    {
      "id": "0183f67a-c9c8-4d98-8490-05780936a81d",
      "name": "San Diego CPA",
      "category_key": "professional-services",
      "reason": "Invalid or unusable URL",
      "url": "https://www.google.com/search?tbm=isch&q=San+Diego+CPA+logo"
    },
    {
      "id": "296ba865-0f03-4077-b164-94b086ad5ade",
      "name": "San Diego Defenders",
      "category_key": "professional-services",
      "reason": "Invalid or unusable URL",
      "url": "https://m.facebook.com/SanDiegoCriminalDefenseLawyers/photos/a.10203261572886596/10203261572886596/?type=3"
    },
    {
      "id": "70cc0e69-3029-4154-a640-bd43ce8d623a",
      "name": "San Diego Personal Injury Lawyer - Mova Law Group",
      "category_key": "professional-services",
      "reason": "Invalid or unusable URL",
      "url": "(empty)"
    },
    {
      "id": "eedd9a79-33ce-4bf5-815f-da730a98010f",
      "name": "San Diego Tax Professionals",
      "category_key": "professional-services",
      "reason": "Invalid or unusable URL",
      "url": "https://www.google.com/search?tbm=isch&q=San+Diego+Tax+Professionals+logo"
    },
    {
      "id": "8958f41a-98db-4958-bcd6-8f7ae31d58c5",
      "name": "South Bay PC Services",
      "category_key": "professional-services",
      "reason": "Invalid or unusable URL",
      "url": "https://www.google.com/search?tbm=isch&q=South+Bay+PC+Services+logo"
    },
    {
      "id": "d8ecb9bb-edbd-4bea-afc8-d69632e21bb9",
      "name": "SVA Tax Services - San Diego",
      "category_key": "professional-services",
      "reason": "Invalid or unusable URL",
      "url": "https://www.google.com/search?tbm=isch&q=SVA+Tax+Services+-+San+Diego+logo"
    },
    {
      "id": "71a6d494-776f-41e7-8b0a-5235e3a75611",
      "name": "T & S Tax Solutions",
      "category_key": "professional-services",
      "reason": "Invalid or unusable URL",
      "url": "https://www.google.com/search?tbm=isch&q=T+%26+S+Tax+Solutions+logo"
    },
    {
      "id": "3b06b922-1eea-4639-9c41-a76aa987381a",
      "name": "The Law Office of Araceli Tovar, APC",
      "category_key": "professional-services",
      "reason": "Invalid or unusable URL",
      "url": "https://www.google.com/search?tbm=isch&q=The+Law+Office+of+Araceli+Tovar,+APC+logo"
    },
    {
      "id": "0918bc72-d951-4dd4-8863-4b0421659758",
      "name": "The Law Office of Giovanna Gallo",
      "category_key": "professional-services",
      "reason": "Invalid or unusable URL",
      "url": "https://www.google.com/search?tbm=isch&q=The+Law+Office+of+Giovanna+Gallo+logo"
    },
    {
      "id": "732f3ee8-661c-4755-819d-4b761dc1e622",
      "name": "The Law Office of James L. Hassey",
      "category_key": "professional-services",
      "reason": "Invalid or unusable URL",
      "url": "https://www.google.com/search?tbm=isch&q=The+Law+Office+of+James+L.+Hassey+logo"
    },
    {
      "id": "897b6cf7-c68c-4991-bba8-10b2af8e36bc",
      "name": "The Sexton Law Firm",
      "category_key": "professional-services",
      "reason": "Invalid or unusable URL",
      "url": "https://www.instagram.com/p/CIEQywmDYDZ/media/?size=l"
    },
    {
      "id": "8cede010-b890-451f-8cc5-f9cdb57b80c6",
      "name": "Veteran Adviser",
      "category_key": "professional-services",
      "reason": "Invalid or unusable URL",
      "url": "(empty)"
    },
    {
      "id": "a672d578-cecd-4f37-bd4a-c32f2e2a9cca",
      "name": "Cafe La Maze",
      "category_key": "restaurants-cafes",
      "reason": "Invalid or unusable URL",
      "url": "https://www.facebook.com/cafelamaze/?__tn__=-UC[R]"
    },
    {
      "id": "d2a26e38-e100-48b6-acd7-e994a6586132",
      "name": "Caffe Tazza",
      "category_key": "restaurants-cafes",
      "reason": "Invalid or unusable URL",
      "url": "https://www.instagram.com/caffetazzacv/p/C3OYWP4vrdP/?hl=am-et"
    },
    {
      "id": "bb686786-b8f0-4db6-870c-72b9e2f571a5",
      "name": "Chiroy's Cafe",
      "category_key": "restaurants-cafes",
      "reason": "Invalid or unusable URL",
      "url": "https://www.facebook.com/Chiroyscafe/photos/"
    },
    {
      "id": "587cb460-7eaa-4a51-ba43-ae802aee3863",
      "name": "everbowl",
      "category_key": "restaurants-cafes",
      "reason": "Invalid or unusable URL",
      "url": "(empty)"
    },
    {
      "id": "4a5c10ad-fedb-45c5-a8a1-643f73230a46",
      "name": "Friends of Friends",
      "category_key": "restaurants-cafes",
      "reason": "Invalid or unusable URL",
      "url": "https://www.instagram.com/wearefof/"
    },
    {
      "id": "28cbbdba-76a7-4bda-9721-349ecdbb3b19",
      "name": "Himalayan House Restaurant",
      "category_key": "restaurants-cafes",
      "reason": "Invalid or unusable URL",
      "url": "(empty)"
    },
    {
      "id": "d81f9b26-18dc-45ea-ba69-c004c968733c",
      "name": "Island Style Sushi",
      "category_key": "restaurants-cafes",
      "reason": "Invalid or unusable URL",
      "url": "https://www.instagram.com/reel/DIULT2NvX-Z"
    },
    {
      "id": "729a87de-f433-4e80-aab5-39658f2bb796",
      "name": "Mango Mango Fresh and Healthy",
      "category_key": "restaurants-cafes",
      "reason": "Invalid or unusable URL",
      "url": "(empty)"
    },
    {
      "id": "f5aa7da0-0ee3-40a9-833f-d9acc29c2e46",
      "name": "Manna Heaven BBQ - National City",
      "category_key": "restaurants-cafes",
      "reason": "Invalid or unusable URL",
      "url": "https://www.mannaheavenbbq.com/new-page-34"
    },
    {
      "id": "b71ea287-8100-4918-aecc-b02f8dc93db4",
      "name": "Mujer Divina Burrito & Coffee House Chula Vista",
      "category_key": "restaurants-cafes",
      "reason": "Invalid or unusable URL",
      "url": "(empty)"
    },
    {
      "id": "bde48255-5800-4dba-9db0-b0d6b64bc9a3",
      "name": "OMG Crepes",
      "category_key": "restaurants-cafes",
      "reason": "Invalid or unusable URL",
      "url": "https://www.instagram.com/omg.crepes"
    },
    {
      "id": "34f7882d-fbec-4bb3-abf8-71f4baf28688",
      "name": "Rising Dragon Chinese Restaurant",
      "category_key": "restaurants-cafes",
      "reason": "Invalid or unusable URL",
      "url": "https://maps.roadtrippers.com/places/2803083/photos"
    },
    {
      "id": "2520cc71-fcfc-41ea-ab2a-51a6fa9bbdc5",
      "name": "Starbucks",
      "category_key": "restaurants-cafes",
      "reason": "Invalid or unusable URL",
      "url": "https://www.instagram.com/p/CKN1q-Yh8T1/media/?size=l"
    },
    {
      "id": "0b353392-2c71-4a43-a497-c1d12ec26ebe",
      "name": "Tacos El Franc",
      "category_key": "restaurants-cafes",
      "reason": "Invalid or unusable URL",
      "url": "https://www.tripadvisor.com/LocationPhotoDirectLink-g150776-d6774828-i450042439-Tacos_El_Franc-Tijuana_Baja_California.html"
    },
    {
      "id": "1d6f03c3-2602-44db-8e5b-84e90792388e",
      "name": "Taqueria Revolucion",
      "category_key": "restaurants-cafes",
      "reason": "Invalid or unusable URL",
      "url": "https://www.tacosrevo.com/gallery/"
    },
    {
      "id": "64054c53-e582-49e9-8262-c1919781c77c",
      "name": "The Mental Bar- Coffee, Tea & Wellness",
      "category_key": "restaurants-cafes",
      "reason": "Invalid or unusable URL",
      "url": "https://www.instagram.com/p/DFTFHztiQzd/media/?size=l"
    }
  ],
  "failed": []
}